README.txt
setup.py
gsquickstart/__init__.py
gsquickstart/release.py
gsquickstart/template.py
gsquickstart.egg-info/PKG-INFO
gsquickstart.egg-info/SOURCES.txt
gsquickstart.egg-info/dependency_links.txt
gsquickstart.egg-info/entry_points.txt
gsquickstart.egg-info/not-zip-safe
gsquickstart.egg-info/requires.txt
gsquickstart.egg-info/top_level.txt
gsquickstart/static/images/Thumbs.db
gsquickstart/static/images/favicon.ico
gsquickstart/static/images/tg_under_the_hood.png
gsquickstart/static/images/under_the_hood_blue.png
gsquickstart/templates/__init__.py
gsquickstart/templates/quickstart/.project_tmpl
gsquickstart/templates/quickstart/setup.py_tmpl
gsquickstart/templates/quickstart/+package+/config/app.cfg_tmpl
gsquickstart/templates/quickstart/+package+/templates/login.html
gsquickstart/templates/quickstart/+package+/templates/master.html
gsquickstart/templates/quickstart/+package+/templates/welcome.html
