Metadata-Version: 1.0
Name: gsquickstart
Version: 1.0
Summary: TurboGears Genshi quickstart template
Home-page: http://trac.turbogears.org/browser/projects/GenshiQuickStart
Author: Fred Lin
Author-email: gasolin+tg@gmail.com
License: MIT
Download-URL: http://www.python.org/pypi/gsquickstart/
Keywords: turbogears.quickstart.template
Platform: UNKNOWN
Classifier: Development Status :: 4 - Beta
Classifier: Environment :: Console
Classifier: License :: OSI Approved :: MIT License
Classifier: Operating System :: OS Independent
Classifier: Programming Language :: Python
Classifier: Topic :: Software Development :: Libraries :: Python Modules
Classifier: Framework :: TurboGears
